gimi9_tree_view/__init__.py
gimi9_tree_view/treeview.py
gimi9_tree_view-0.6.0.dist-info/LICENSE
gimi9_tree_view-0.6.0.dist-info/METADATA
gimi9_tree_view-0.6.0.dist-info/WHEEL
gimi9_tree_view-0.6.0.dist-info/entry_points.txt
gimi9_tree_view-0.6.0.dist-info/top_level.txt
gimi9_tree_view-0.6.0.dist-info/RECORD
