Metadata-Version: 2.1
Name: gimi9_tree_view
Version: 0.6.0
Summary: Visual treeview utility
Home-page: https://github.com/gisman/tree-view
Author: gisman
Author-email: gisman@gmail.com
License: Apache-2.0
Classifier: Programming Language :: Python :: 3
Classifier: Operating System :: POSIX :: Linux
Requires-Python: >=3.2
License-File: LICENSE
Requires-Dist: tomli
Requires-Dist: wcwidth
Requires-Dist: argparse
